{"/about/":{"data":{"":"","manjunath-beli#Manjunath Beli":"End User Computing Architect\nA Microsoft certified Workspace Solution Engineer with 12+ years experience of Consulting, Design and Administer tools \u0026 technology related to End User Computing. Proficient in Modern Workplace Services, SCCM, Intune, PowerShell and Azure cloud technologies.\nConnect with Me "},"title":"About"},"/blog/markdown-is-a-must/":{"data":{"":"","markdown-is-everywhere#Markdown is everywhere":"It started with simple markup language for notes talking."},"title":"Markdown Is a Must"}}